odoo9_addon_openeducat_l10n_in_admission-9.0.2.4.0-py2.7-nspkg.pth
odoo_addons/openeducat_l10n_in_admission/__openerp__.py
odoo_addons/openeducat_l10n_in_admission/__init__.py
odoo_addons/openeducat_l10n_in_admission/models/admission.py
odoo_addons/openeducat_l10n_in_admission/models/__init__.py
odoo_addons/openeducat_l10n_in_admission/i18n/openeducat_l10n_in_admission.pot
odoo_addons/openeducat_l10n_in_admission/views/admission_view.xml
odoo_addons/openeducat_l10n_in_admission/demo/op.admission.csv
odoo_addons/openeducat_l10n_in_admission/static/description/openeducat_logo.png
odoo_addons/openeducat_l10n_in_admission/static/description/indian_openeducat_admission_banner.jpg
odoo_addons/openeducat_l10n_in_admission/static/description/l10in_admission.png
odoo_addons/openeducat_l10n_in_admission/static/description/index.html
odoo_addons/openeducat_l10n_in_admission/static/description/icon.png
odoo9_addon_openeducat_l10n_in_admission-9.0.2.4.0.dist-info/top_level.txt
odoo9_addon_openeducat_l10n_in_admission-9.0.2.4.0.dist-info/WHEEL
odoo9_addon_openeducat_l10n_in_admission-9.0.2.4.0.dist-info/RECORD
odoo9_addon_openeducat_l10n_in_admission-9.0.2.4.0.dist-info/metadata.json
odoo9_addon_openeducat_l10n_in_admission-9.0.2.4.0.dist-info/DESCRIPTION.rst
odoo9_addon_openeducat_l10n_in_admission-9.0.2.4.0.dist-info/METADATA
odoo9_addon_openeducat_l10n_in_admission-9.0.2.4.0.dist-info/namespace_packages.txt
